urlcheck_smith/__init__.py
urlcheck_smith/check.py
urlcheck_smith/classify.py
urlcheck_smith/cli.py
urlcheck_smith/extract.py
urlcheck_smith/models.py
urlcheck_smith/data/rules_eu.yaml
urlcheck_smith/data/rules_global.yaml
urlcheck_smith/data/rules_japan.yaml
urlcheck_smith/data/site_categories.yaml
urlcheck_smith-0.2.1.dist-info/licenses/LICENSE
urlcheck_smith-0.2.1.dist-info/METADATA
urlcheck_smith-0.2.1.dist-info/WHEEL
urlcheck_smith-0.2.1.dist-info/entry_points.txt
urlcheck_smith-0.2.1.dist-info/top_level.txt
urlcheck_smith-0.2.1.dist-info/RECORD
