Metadata-Version: 2.4
Name: urlcheck-smith
Version: 0.2.1
Summary: Minimal URL extraction / classification / HTTP check pipeline.
Author: Eiichi Yamamoto
License-Expression: MIT
Requires-Python: >=3.8
License-File: LICENSE
Requires-Dist: requests>=2.31.0
Requires-Dist: PyYAML>=6.0.0
Provides-Extra: dev
Requires-Dist: pytest>=9.0.0; extra == "dev"
Dynamic: license-file
